spliceai/__clean_main__.py
spliceai/__init__.py
spliceai/__main__.py
spliceai/normalise_chrom.py
spliceai/utils.py
spliceai/annotations/grch37.txt
spliceai/annotations/grch38.txt
spliceai/models/spliceai1.h5
spliceai/models/spliceai2.h5
spliceai/models/spliceai3.h5
spliceai/models/spliceai4.h5
spliceai/models/spliceai5.h5
spliceai-1.3.1.dist-info/METADATA
spliceai-1.3.1.dist-info/RECORD
spliceai-1.3.1.dist-info/WHEEL
spliceai-1.3.1.dist-info/entry_points.txt
spliceai-1.3.1.dist-info/top_level.txt
