Metadata-Version: 2.1
Name: spliceai
Version: 1.3.1
Summary: SpliceAI: A deep learning-based tool to identify splice variants
Home-page: https://github.com/illumina/SpliceAI
Author: Kishore Jaganathan
Author-email: kishorejaganathan@gmail.com
License: GPLv3
Platform: UNKNOWN
Provides-Extra: gpu
Provides-Extra: cpu
Requires-Dist: keras (>=2.0.5)
Requires-Dist: pyfaidx (>=0.5.0)
Requires-Dist: pysam (>=0.10.0)
Requires-Dist: numpy (>=1.14.0)
Requires-Dist: pandas (>=0.24.2)
Provides-Extra: cpu
Requires-Dist: tensorflow (>=1.2.0); extra == 'cpu'
Provides-Extra: gpu
Requires-Dist: tensorflow-gpu (>=1.2.0); extra == 'gpu'
